Metadata-Version: 2.4
Name: taoshi-ts-exchange-ccxt
Version: 0.0.1
Summary: This package name is reserved by Taoshi Inc
Home-page: https://taoshi.io/
Author: Taoshi Inc
Author-email: python@taoshi.io
License-File: LICENSE.txt
Dynamic: author
Dynamic: author-email
Dynamic: description
Dynamic: description-content-type
Dynamic: home-page
Dynamic: license-file
Dynamic: summary
